digging/__init__.py
digging/digger/__init__.py
digging/digger/base_digger.py
digging/digger/bo_digger.py
digging/digger/ga_digger.py
digging/digger/pg_rl_digger.py
digging/digger/ppo_rl_digger.py
digging/digger/random_digger.py
digging/digger/rl_digger.py
digging/model/__init__.py
digging/model/rl_model.py
digging/model/rnn_model.py
digging/problem/__init__.py
digging/problem/data_pool.py
digging/problem/problem_env.py
digging/problem/problem_handler.py
digging/problem/space.py
digging/utils/__init__.py
digging/utils/event.py
digging/utils/logger.py
DIgging-0.0.0.1.dist-info/LICENSE
DIgging-0.0.0.1.dist-info/METADATA
DIgging-0.0.0.1.dist-info/WHEEL
DIgging-0.0.0.1.dist-info/top_level.txt
DIgging-0.0.0.1.dist-info/RECORD
